{
    "id": "74",
    "slug": "cooper-spur-ski-area",
    "name": "Cooper Spur Ski Area",
    "region": "West",
    "description": "We are located on the beautiful North side of Mt. Hood. Our combination of affordable pricing, beginner to intermediate-level terrain, and the manageable size of our ski area, present an ideal outing for families. Steeped in history, Cooper Spur is one of the oldest ski areas in North America! Our ski area utilizes a Double Chairli and Beginner Rope Tow, with 9 Runs of Fun for Skiing and snowboarding, 50 Acres of Beginner and intermediate-level terrain, with over 400 feet of vertical (3,969 to 4,400\u2032). We offer Lessons, a Rental Shop, and a Historic Alpine Lodge providing snacks and refreshments including a covered outdoor deck and picnic area.",
    "website": "https://www.cooperspur.com",
    "trails": 9,
    "lifts": 2,
    "acres": 50,
    "trail_length_km": null,
    "trail_length_mi": null,
    "is_cross_country": false,
    "is_dog_friendly": false,
    "has_snowshoeing": false,
    "terrain_parks": false,
    "night_skiing": true,
    "vertical_base_ft": 3969,
    "vertical_summit_ft": 4400,
    "vertical_elevation_ft": 400,
    "difficulty_beginner": 20,
    "difficulty_intermediate": 70,
    "difficulty_advanced": 10,
    "snowfall_average_in": 46,
    "snowfall_high_in": 89
}