{
    "id": "349",
    "slug": "hatley-pointe",
    "name": "Hatley Pointe",
    "region": "Mid-Atlantic",
    "description": "Hatley Pointe is a boutique mountain resort built for those who seek to embrace the spirit of adventure. With a peak elevation of 4700 ft and both beginner and expert trails, Hatley Pointe has something for everyone. Hatley Pointe also offers an incredible atmosphere for apres ski inside the newly renovated base lodge. Hatley Pointe offers a full-service restaurant and bar as well as quick on-the-go food and beverage options.",
    "website": "https://www.hatleypointe.com/",
    "trails": 17,
    "lifts": 4,
    "acres": 52,
    "trail_length_km": null,
    "trail_length_mi": null,
    "is_cross_country": false,
    "is_dog_friendly": false,
    "has_snowshoeing": false,
    "terrain_parks": true,
    "night_skiing": true,
    "vertical_base_ft": 4000,
    "vertical_summit_ft": 4700,
    "vertical_elevation_ft": 700,
    "difficulty_beginner": 25,
    "difficulty_intermediate": 60,
    "difficulty_advanced": 15,
    "snowfall_average_in": 65,
    "snowfall_high_in": 90
}